talkkeeper/__init__.py
talkkeeper/__main__.py
talkkeeper/cli/application.py
talkkeeper/core/settings.py
talkkeeper/handlers/audio.py
talkkeeper/handlers/events.py
talkkeeper/handlers/video.py
talkkeeper/packages/index.py
talkkeeper/packages/s3.py
talkkeeper/packages/uploader.py
talkkeeper/talkkeeper.py
talkkeeper-0.2.2.dist-info/entry_points.txt
talkkeeper-0.2.2.dist-info/WHEEL
talkkeeper-0.2.2.dist-info/METADATA
talkkeeper-0.2.2.dist-info/RECORD
